Workbook

Sheet Dashboard
B2: SALES PERFORMANCE DASHBOARD
B4: Total Revenue | E4: Total Orders | H4: Avg Order Value | K4: Unique Customers
B5: =SUM(Sales_Data!J:J) -> 2803407.8 | E5: =COUNTA(Sales_Data!A:A)-1 -> 250 | H5: =AVERAGE(Sales_Data!J:J) -> 11213.631 | K5: 12

Sheet Summary_Tables
A1: SALES SUMMARY ANALYSIS
A3: Sales by Region | F3: Sales by Category
A4: Region | B4: Total Sales | C4: Order Count | D4: Avg Order Value | F4: Category | G4: Total Sales | H4: Percentage
A5: North | B5: =SUMIF(Sales_Data!D:D,A5,Sales_Data!J:J) -> 480694.41 | C5: =COUNTIF(Sales_Data!D:D,A5) -> 54 | D5: =B5/C5 -> 8901.7483 | F5: Electronics | G5: =SUMIF(Sales_Data!F:F,F5,Sales_Data!J:J) -> 689465.13 | H5: =G5/SUM($G$5:$G$9) -> 0.24593822
A6: South | B6: =SUMIF(Sales_Data!D:D,A6,Sales_Data!J:J) -> 597491.74 | C6: =COUNTIF(Sales_Data!D:D,A6) -> 52 | D6: =B6/C6 -> 11490.226 | F6: Accessories | G6: =SUMIF(Sales_Data!F:F,F6,Sales_Data!J:J) -> 564846.26 | H6: =G6/SUM($G$5:$G$9) -> 0.20148558
A7: East | B7: =SUMIF(Sales_Data!D:D,A7,Sales_Data!J:J) -> 496192.41 | C7: =COUNTIF(Sales_Data!D:D,A7) -> 41 | D7: =B7/C7 -> 12102.254 | F7: Peripherals | G7: =SUMIF(Sales_Data!F:F,F7,Sales_Data!J:J) -> 525666.89 | H7: =G7/SUM($G$5:$G$9) -> 0.18750996
A8: West | B8: =SUMIF(Sales_Data!D:D,A8,Sales_Data!J:J) -> 570173.08 | C8: =COUNTIF(Sales_Data!D:D,A8) -> 50 | D8: =B8/C8 -> 11403.462 | F8: Computing | G8: =SUMIF(Sales_Data!F:F,F8,Sales_Data!J:J) -> 499014.34 | H8: =G8/SUM($G$5:$G$9) -> 0.17800276
A9: Central | B9: =SUMIF(Sales_Data!D:D,A9,Sales_Data!J:J) -> 658856.2 | C9: =COUNTIF(Sales_Data!D:D,A9) -> 53 | D9: =B9/C9 -> 12431.249 | F9: Mobile | G9: =SUMIF(Sales_Data!F:F,F9,Sales_Data!J:J) -> 524415.21 | H9: =G9/SUM($G$5:$G$9) -> 0.18706347
A10: TOTAL | B10: =SUM(B5:B9) -> 2803407.8 | C10: =SUM(C5:C9) -> 250 | D10: =B10/C10 -> 11213.631
A12: Top 10 Products by Revenue | F12: Monthly Sales Trend (2024)
A13: Rank | B13: Product | C13: Total Sales | D13: Units Sold | F13: Month | G13: Sales | H13: Orders
A14: 1 | B14: Laptop | C14: =SUMIF(Sales_Data!E:E,B14,Sales_Data!J:J) -> 188647.7 | D14: =SUMIF(Sales_Data!E:E,B14,Sales_Data!G:G) -> 195 | F14: Jan | G14: =SUMIFS(Sales_Data!J:J,Sales_Data!B:B,">="&DATE(2024,1,1),Sales_Data!B:B,"<"&DATE(2024,2,1)) -> 184628.41 | H14: =COUNTIFS(Sales_Data!B:B,">="&DATE(2024,1,1),Sales_Data!B:B,"<"&DATE(2024,2,1)) -> 20
A15: 2 | B15: Monitor | C15: =SUMIF(Sales_Data!E:E,B15,Sales_Data!J:J) -> 213456.83 | D15: =SUMIF(Sales_Data!E:E,B15,Sales_Data!G:G) -> 199 | F15: Feb | G15: =SUMIFS(Sales_Data!J:J,Sales_Data!B:B,">="&DATE(2024,2,1),Sales_Data!B:B,"<"&DATE(2024,3,1)) -> 394267.56 | H15: =COUNTIFS(Sales_Data!B:B,">="&DATE(2024,2,1),Sales_Data!B:B,"<"&DATE(2024,3,1)) -> 34
A16: 3 | B16: Tablet | C16: =SUMIF(Sales_Data!E:E,B16,Sales_Data!J:J) -> 302483.7 | D16: =SUMIF(Sales_Data!E:E,B16,Sales_Data!G:G) -> 236 | F16: Mar | G16: =SUMIFS(Sales_Data!J:J,Sales_Data!B:B,">="&DATE(2024,3,1),Sales_Data!B:B,"<"&DATE(2024,4,1)) -> 180556.09 | H16: =COUNTIFS(Sales_Data!B:B,">="&DATE(2024,3,1),Sales_Data!B:B,"<"&DATE(2024,4,1)) -> 22
A17: 4 | B17: Smartphone | C17: =SUMIF(Sales_Data!E:E,B17,Sales_Data!J:J) -> 298380.82 | D17: =SUMIF(Sales_Data!E:E,B17,Sales_Data!G:G) -> 315 | F17: Apr | G17: =SUMIFS(Sales_Data!J:J,Sales_Data!B:B,">="&DATE(2024,4,1),Sales_Data!B:B,"<"&DATE(2024,5,1)) -> 166930.15 | H17: =COUNTIFS(Sales_Data!B:B,">="&DATE(2024,4,1),Sales_Data!B:B,"<"&DATE(2024,5,1)) -> 18
A18: 5 | B18: Printer | C18: =SUMIF(Sales_Data!E:E,B18,Sales_Data!J:J) -> 220122.98 | D18: =SUMIF(Sales_Data!E:E,B18,Sales_Data!G:G) -> 213 | F18: May | G18: =SUMIFS(Sales_Data!J:J,Sales_Data!B:B,">="&DATE(2024,5,1),Sales_Data!B:B,"<"&DATE(2024,6,1)) -> 183340.84 | H18: =COUNTIFS(Sales_Data!B:B,">="&DATE(2024,5,1),Sales_Data!B:B,"<"&DATE(2024,6,1)) -> 19
A19: 6 | B19: Scanner | C19: =SUMIF(Sales_Data!E:E,B19,Sales_Data!J:J) -> 367021.58 | D19: =SUMIF(Sales_Data!E:E,B19,Sales_Data!G:G) -> 306 | F19: Jun | G19: =SUMIFS(Sales_Data!J:J,Sales_Data!B:B,">="&DATE(2024,6,1),Sales_Data!B:B,"<"&DATE(2024,7,1)) -> 166433.38 | H19: =COUNTIFS(Sales_Data!B:B,">="&DATE(2024,6,1),Sales_Data!B:B,"<"&DATE(2024,7,1)) -> 15
A20: 7 | B20: Headphones | C20: =SUMIF(Sales_Data!E:E,B20,Sales_Data!J:J) -> 275217.89 | D20: =SUMIF(Sales_Data!E:E,B20,Sales_Data!G:G) -> 257 | F20: Jul | G20: =SUMIFS(Sales_Data!J:J,Sales_Data!B:B,">="&DATE(2024,7,1),Sales_Data!B:B,"<"&DATE(2024,8,1)) -> 255253.48 | H20: =COUNTIFS(Sales_Data!B:B,">="&DATE(2024,7,1),Sales_Data!B:B,"<"&DATE(2024,8,1)) -> 21
A21: 8 | B21: Webcam | C21: =SUMIF(Sales_Data!E:E,B21,Sales_Data!J:J) -> 363106.05 | D21: =SUMIF(Sales_Data!E:E,B21,Sales_Data!G:G) -> 331 | F21: Aug | G21: =SUMIFS(Sales_Data!J:J,Sales_Data!B:B,">="&DATE(2024,8,1),Sales_Data!B:B,"<"&DATE(2024,9,1)) -> 273152.8 | H21: =COUNTIFS(Sales_Data!B:B,">="&DATE(2024,8,1),Sales_Data!B:B,"<"&DATE(2024,9,1)) -> 20
A22: 9 | B22: Keyboard | C22: =SUMIF(Sales_Data!E:E,B22,Sales_Data!J:J) -> 309566.68 | D22: =SUMIF(Sales_Data!E:E,B22,Sales_Data!G:G) -> 239 | F22: Sep | G22: =SUMIFS(Sales_Data!J:J,Sales_Data!B:B,">="&DATE(2024,9,1),Sales_Data!B:B,"<"&DATE(2024,10,1)) -> 194739.2 | H22: =COUNTIFS(Sales_Data!B:B,">="&DATE(2024,9,1),Sales_Data!B:B,"<"&DATE(2024,10,1)) -> 20
A23: 10 | B23: Mouse | C23: =SUMIF(Sales_Data!E:E,B23,Sales_Data!J:J) -> 265403.59 | D23: =SUMIF(Sales_Data!E:E,B23,Sales_Data!G:G) -> 277 | F23: Oct | G23: =SUMIFS(Sales_Data!J:J,Sales_Data!B:B,">="&DATE(2024,10,1),Sales_Data!B:B,"<"&DATE(2024,11,1)) -> 454086.96 | H23: =COUNTIFS(Sales_Data!B:B,">="&DATE(2024,10,1),Sales_Data!B:B,"<"&DATE(2024,11,1)) -> 31
F24: Nov | G24: =SUMIFS(Sales_Data!J:J,Sales_Data!B:B,">="&DATE(2024,11,1),Sales_Data!B:B,"<"&DATE(2024,12,1)) -> 139265.42 | H24: =COUNTIFS(Sales_Data!B:B,">="&DATE(2024,11,1),Sales_Data!B:B,"<"&DATE(2024,12,1)) -> 15
F25: Dec | G25: =SUMIFS(Sales_Data!J:J,Sales_Data!B:B,">="&DATE(2024,12,1),Sales_Data!B:B,"<"&DATE(2024,13,1)) -> 210753.54 | H25: =COUNTIFS(Sales_Data!B:B,">="&DATE(2024,12,1),Sales_Data!B:B,"<"&DATE(2024,13,1)) -> 15

Sheet Charts
A1: DATA VISUALIZATION CHARTS

Sheet Sales_Data
A1: Order_ID | B1: Date | C1: Customer_Name | D1: Region | E1: Product | F1: Category | G1: Quantity | H1: Unit_Price | I1: Discount | J1: Total_Sales | K1: Profit_Margin
A2: ORD10002 | B2: 45550 | C2: Tech Solutions | D2: East | E2: Laptop | F2: Peripherals | G2: 9 | H2: 1942.56 | I2: 0.04 | J2: =G2*H2*(1-I2) -> 16783.718 | K2: 0.37
A3: ORD10003 | B3: 45347 | C3: Global Systems | D3: North | E3: Scanner | F3: Accessories | G3: 3 | H3: 905.53 | I3: 0.24 | J3: =G3*H3*(1-I3) -> 2064.6084 | K3: 0.16
A4: ORD10004 | B4: 45568 | C4: Global Systems | D4: West | E4: Webcam | F4: Accessories | G4: 2 | H4: 788.59 | I4: 0.29 | J4: =G4*H4*(1-I4) -> 1119.7978 | K4: 0.4
A5: ORD10005 | B5: 45512 | C5: Quantum Corp | D5: South | E5: Webcam | F5: Peripherals | G5: 9 | H5: 1305.21 | I5: 0.15 | J5: =G5*H5*(1-I5) -> 9984.8565 | K5: 0.35
A6: ORD10006 | B6: 45395 | C6: Metro Business | D6: South | E6: Monitor | F6: Computing | G6: 17 | H6: 1803.21 | I6: 0.15 | J6: =G6*H6*(1-I6) -> 26056.385 | K6: 0.34
A7: ORD10007 | B7: 45638 | C7: Digital Dynamics | D7: West | E7: Scanner | F7: Mobile | G7: 11 | H7: 1174.2 | I7: 0.22 | J7: =G7*H7*(1-I7) -> 10074.636 | K7: 0.44
A8: ORD10008 | B8: 45477 | C8: Global Systems | D8: North | E8: Keyboard | F8: Electronics | G8: 19 | H8: 1784.2 | I8: 0.13 | J8: =G8*H8*(1-I8) -> 29492.826 | K8: 0.28
A9: ORD10009 | B9: 45349 | C9: Metro Business | D9: North | E9: Printer | F9: Peripherals | G9: 11 | H9: 1363.33 | I9: 0.16 | J9: =G9*H9*(1-I9) -> 12597.169 | K9: 0.16
A10: ORD10010 | B10: 45588 | C10: Future Tech | D10: South | E10: Keyboard | F10: Computing | G10: 14 | H10: 2072.49 | I10: 0.02 | J10: =G10*H10*(1-I10) -> 28434.563 | K10: 0.33
A11: ORD10011 | B11: 45549 | C11: Metro Business | D11: North | E11: Smartphone | F11: Peripherals | G11: 6 | H11: 1374.43 | I11: 0.09 | J11: =G11*H11*(1-I11) -> 7504.3878 | K11: 0.22
A12: ORD10012 | B12: 45510 | C12: Future Tech | D12: South | E12: Headphones | F12: Electronics | G12: 12 | H12: 1869.2 | I12: 0.03 | J12: =G12*H12*(1-I12) -> 21757.488 | K12: 0.44
A13: ORD10013 | B13: 45325 | C13: Smart Enterprises | D13: South | E13: Smartphone | F13: Electronics | G13: 18 | H13: 1224.97 | I13: 0.22 | J13: =G13*H13*(1-I13) -> 17198.579 | K13: 0.41
... A251: ORD10251 | B251: 45527 | C251: Prime Solutions | D251: Central | E251: Mouse | F251: Computing | G251: 19 | H251: 2353.97 | I251: 0.11 | J251: =G251*H251*(1-I251) -> 39805.633 | K251: 0.35

Sheet Formulas_Reference
A1: FORMULAS REFERENCE GUIDE
A3: Function | B3: Purpose | C3: Formula Example | D3: Location | E3: Result Type
A4: SUM | B4: Total revenue calculation | C4: =SUM(Sales_Data!J:J) -> 2803407.8 | D4: Dashboard KPI | E4: Currency
A5: SUMIF | B5: Region-specific sales | C5: =SUMIF(Sales_Data!D:D,"North",Sales_Data!J:J) -> 480694.41 | D5: Summary Tables | E5: Currency
A6: SUMIFS | B6: Monthly sales with dates | C6: =SUMIFS(Sales_Data!J:J,Sales_Data!B:B,">="&DATE(2024,1,1)) -> 2803407.8 | D6: Monthly Trend | E6: Currency
A7: COUNTIF | B7: Count orders by region | C7: =COUNTIF(Sales_Data!D:D,"North") -> 54 | D7: Summary Tables | E7: Number
A8: AVERAGE | B8: Average order value | C8: =AVERAGE(Sales_Data!J:J) -> 11213.631 | D8: Dashboard KPI | E8: Currency
A9: COUNTA | B9: Total number of orders | C9: =COUNTA(Sales_Data!A:A)-1 -> 250 | D9: Dashboard KPI | E9: Number
A10: Division | B10: Calculate percentage | C10: Quantity * Price * (1-Discount) | D10: Category % | E10: Percentage
A11: Multiplication | B11: Total sales calculation | C11: =G2*H2*(1-I2) -> 0 | D11: Sales Data | E11: Currency

Sheet Instructions
A1: EXCEL DASHBOARD - USER GUIDE
A4: Sheet Name | B4: Purpose | C4: Key Features | D4: Usage
A5: Dashboard | B5: Main interactive view | C5: • KPI cards • Interactive charts • Real-time calculations | D5: Primary viewing sheet
A6: Sales_Data | B6: Raw transactional data | C6: • 250 order records • Formatted as Excel table • All calculations reference this | D6: Source data - do not modify
A7: Summary_Tables | B7: Pre-calculated summaries | C7: • Sales by Region • Sales by Category • Top 10 Products • Monthly trends | D7: Referenced by charts
A8: Charts | B8: Standalone visualizations | C8: • Bar charts • Pie charts • Line charts • Product rankings | D8: Individual chart views
A9: Formulas_Reference | B9: Formula documentation | C9: • All formulas explained • Examples and purposes • Result types | D9: Learning and reference
A10: Instructions | B10: This guide | C10: • Sheet descriptions • Navigation tips | D10: Getting started
